lincoln/__init__.py
lincoln/inout.py
lincoln/mobilerobot.py
lincoln/robotarm.py
lincoln/visualize.py
lincoln-0.0.2.dist-info/LICENSE
lincoln-0.0.2.dist-info/METADATA
lincoln-0.0.2.dist-info/WHEEL
lincoln-0.0.2.dist-info/top_level.txt
lincoln-0.0.2.dist-info/RECORD
