Metadata-Version: 2.1
Name: lincoln
Version: 0.0.2
Summary: my personal pip package for
Home-page: https://github.com/lincolnmroth/lincoln
Author: Lincoln Roth
Author-email: lincolnmroth@gmail.com
License: UNKNOWN
Project-URL: Bug Tracker, https://github.com/lincolnmroth/lincoln/issues
Platform: UNKNOWN
Classifier: Programming Language :: Python :: 3
Classifier: License :: OSI Approved :: MIT License
Classifier: Operating System :: OS Independent
Requires-Python: >=3.6
